{
	"config":[
		{
			"environment":"online",
			"gateway_cloud":{
				"addr":"g-aicloud.alibaba.com",
				"port":443,
				"protocol_ver":"1.0",
				"use_ssl":true
			},
			"speech":{
				"addr":"asr-aicloud.alibaba.com",
				"audio_type":"ogg",
				"compress":"speex",
				"coretype":"cn.asr.rec",
				"port":443,
				"quality":8,
				"res":"aihome",
				"use_ssl":true
			},
			"system":{
				"biz_group":"QQFEMmPF",
				"biz_type":"FIIL",
				"ca_path":"/data/geniesdk/config/ca.pem",
				"dev_secret":"a53afc76-6e52-4c01-8492-ab76d3ff9e72"
			}
		},
		{
			"environment":"pre",
			"gateway_cloud":{
				"addr":"gdev-aicloud.alibaba.com",
				"port":443,
				"protocol_ver":"1.0",
				"use_ssl":true
			},
			"speech":{
				"addr":"asr-aicloud.alibaba.com",
				"audio_type":"ogg",
				"compress":"speex",
				"coretype":"cn.asr.rec",
				"port":443,
				"quality":8,
				"res":"aihome",
				"use_ssl":true
			},
			"system":{
				"biz_group":"QQFEMmPF",
				"biz_type":"FIIL",
				"ca_path":"/data/geniesdk/config/ca.pem",
				"dev_secret":"a53afc76-6e52-4c01-8492-ab76d3ff9e72"
			}
		}
	],
	"env":"online",
	"featureList":{
		"askCmdQueue":0,
		"countDown":0,
		"nightLight":0,
		"otaUpdate":0,
		"remoteDebug":0,
		"utpControl":1,
		"voiceMessage":1,
		"volumeCtrl":1
	},
	"version":"20180425"
}